README.rst
setup.py
pip_init/__init__.py
pip_init/templates.py
pip_init.egg-info/PKG-INFO
pip_init.egg-info/SOURCES.txt
pip_init.egg-info/dependency_links.txt
pip_init.egg-info/entry_points.txt
pip_init.egg-info/pbr.json
pip_init.egg-info/top_level.txt