Metadata-Version: 1.1
Name: pip-init
Version: 0.3.0
Summary: pip-init to generate a base setup.py file
Home-page: https://github.com/juanpabloaj/pip-init
Author: JuanPablo AJ
Author-email: jpabloaj@gmail.com
License: MIT
Platform: UNKNOWN
Classifier: Programming Language :: Python
Classifier: Programming Language :: Python :: 2.7
Classifier: Programming Language :: Python :: 3.4
